krutrimpy/__init__.py
krutrimpy/krutrim.py
krutrimpy-0.0.1.dist-info/LICENSE
krutrimpy-0.0.1.dist-info/METADATA
krutrimpy-0.0.1.dist-info/WHEEL
krutrimpy-0.0.1.dist-info/top_level.txt
krutrimpy-0.0.1.dist-info/RECORD
