Metadata-Version: 2.1
Name: krutrimpy
Version: 0.0.1
Summary: An unofficial wrapper for Krutrim
Home-page: https://github.com/Assassinumz/krutrimpy
Author: Umraz Khan
Author-email: kumraz858@gmail.com
Keywords: ola,krutrim,olakrutrim,krutrim wrapper
Classifier: Development Status :: 3 - Alpha
Classifier: Programming Language :: Python :: 3
Requires-Python: >=3.10
License-File: LICENSE
Requires-Dist: requests
